switch_counter.v
module switch_counter(
    input clk,
    input reset,
    input signal,
    output reg [31:0] count
);

reg prev;

always @(posedge clk or posedge reset) begin
    if(reset) begin
        count <= 0;
        prev <= 0;
    end
    else begin
        if(signal != prev)
            count <= count + 1;
        prev <= signal;
    end
end

endmodule

dummy_alu.v
module dummy_alu(
    input clk,
    output reg [7:0] out
);

initial out = 0;

always @(posedge clk)
    out <= out + 1;

endmodule

power_controller.v
module power_controller(
    input clk,
    input reset,
    input predict,          
    output master_clk,       // Always ON
    output [3:0] worker_clks,
    output [2:0] active_count // Number for your display (0-5)
);
    reg enable;
    reg [5:0] warmup = 0;
    reg latch_en;

    // Logic: Enable workers if predict is high AND warmup done
    always @(posedge clk or posedge reset) begin
        if(reset) begin
            warmup <= 0;
            enable <= 1;
        end else begin
            if(warmup < 4) begin
                warmup <= warmup + 1;
                enable <= 1;
            end else begin
                enable <= predict;
            end
        end
    end

    // Safe Latch-based gating
    always @(clk or enable) begin
        if (!clk) latch_en <= enable;
    end

    assign master_clk = clk;
    
    // If predict is 1, all 4 workers turn on. If 0, they turn off.
    assign worker_clks = {4{clk & latch_en}};
    
    // Display Logic: 1 Master + (4 workers IF enable is high)
    assign active_count = enable ? 3'd5 : 3'd1;

endmodule

perceptron.v
module perceptron(
    input [7:0] x,
    output reg predict
);

// ------------VALUES------------
parameter signed W0 = 80;
parameter signed W1 = 96;
parameter signed W2 = 80;
parameter signed W3 = 112;
parameter signed W4 = 80;
parameter signed W5 = 80;
parameter signed W6 = 80;
parameter signed W7 = 96;
parameter signed BIAS = -304;
// -----------------------------

integer sum;

always @(*) begin
    sum = BIAS;
    if(x[0]) sum = sum + W0;
    if(x[1]) sum = sum + W1;
    if(x[2]) sum = sum + W2;
    if(x[3]) sum = sum + W3;
    if(x[4]) sum = sum + W4;
    if(x[5]) sum = sum + W5;
    if(x[6]) sum = sum + W6;
    if(x[7]) sum = sum + W7;

    if(sum >= 0)
        predict = 1;
    else
        predict = 0;
end
endmodule

history_buffer.v
module history_buffer(
    input clk,
    input reset,
    input workload_bit,
    output reg [7:0] hist
);
always @(posedge clk or posedge reset) begin
    if(reset)
        hist <= 8'b0;
    else
        hist <= {hist[6:0], workload_bit};
end
endmodule

tb.v
`timescale 1ns / 1ps
module tb;
    reg clk = 0;
    reg reset = 1;
    reg workload;

    // Interconnects
    wire [7:0] hist;
    wire predict;
    wire master_clk;
    wire [3:0] worker_clks; // 4 worker clocks
    wire [2:0] active_count;

    // ALU Outputs (These caused your error earlier - they must be declared!)
    wire [7:0] master_out;
    wire [7:0] worker_out;

    // Power Measurement Counters
    wire [31:0] master_toggles;
    wire [31:0] worker_toggles;

    
    history_buffer HB(clk, reset, workload, hist);
    perceptron P(hist, predict);
    
    
    power_controller PC(clk, reset, predict, master_clk, worker_clks, active_count);

    dummy_alu MASTER_CORE (
        .clk(master_clk), 
        .out(master_out)
    );

    // The Worker Core receives one of the gated clocks (worker_clks[0])
    dummy_alu WORKER_CORE (
        .clk(worker_clks[0]), 
        .out(worker_out)
    );

    // Measures how often the Master toggles vs the Worker
    switch_counter MASTER_METER (master_clk, reset, master_out[0], master_toggles);
    switch_counter WORKER_METER (worker_clks[0], reset, worker_out[0], worker_toggles);


    // Clock Generation
    always #5 clk = ~clk;

    // Variables for Power Calculation
    integer baseline_power;
    integer optimized_power;
    integer saved_power;
    real percent_saved;

    initial begin
        $dumpfile("wave.vcd");
        $dumpvars(0, tb);

        // Header
        $display("---------------------------------------------------");
        $display("   ML-ADAPTIVE CORE MONITOR STARTING");
        $display("---------------------------------------------------");
        // Monitor changes in core count
        $monitor("Time: %0t | Workload: %b | Prediction: %b | ACTIVE CORES: %0d", 
                 $time, workload, predict, active_count);

        reset = 1; 
        #20 reset = 0;

        $display("\n[DEMO] Phase 1: High Workload Burst...");
        repeat(30) begin workload = 1; #10; end

        $display("\n[DEMO] Phase 2: System Idle (Power Saving Mode)...");
        repeat(200) begin workload = 0; #10; end

        $display("\n[DEMO] Phase 3: Dynamic Scaling...");
        repeat(50) begin 
            workload = ($random % 2); 
            #10; 
        end
        
        #100;

        baseline_power = master_toggles * 5; 

        optimized_power = master_toggles + (worker_toggles * 4);

        saved_power = baseline_power - optimized_power;
        percent_saved = (saved_power * 100.0) / baseline_power;

        $display("\n===================================================");
        $display("             POWER EFFICIENCY REPORT               ");
        $display("===================================================");
        $display("Total Toggles (Unoptimized System) : %0d", baseline_power);
        $display("Total Toggles (Your Adaptive System) : %0d", optimized_power);
        $display("---------------------------------------------------");
        $display("SWITCHING REDUCTION                : %0d toggles", saved_power);
        $display("ESTIMATED POWER SAVINGS            : %0.2f %%", percent_saved);
        $display("===================================================\n");

        $finish;
    end
endmodule

wave.vcd
$date
	Fri Jan 02 14:33:07 2026
$end
$version
	Icarus Verilog
$end
$timescale
	1ps
$end
$scope module tb $end
$var wire 32 ! worker_toggles [31:0] $end
$var wire 8 " worker_out [7:0] $end
$var wire 4 # worker_clks [3:0] $end
$var wire 1 $ predict $end
$var wire 32 % master_toggles [31:0] $end
$var wire 8 & master_out [7:0] $end
$var wire 1 ' master_clk $end
$var wire 8 ( hist [7:0] $end
$var wire 3 ) active_count [2:0] $end
$var reg 1 * clk $end
$var reg 1 + reset $end
$var reg 1 , workload $end
$var integer 32 - baseline_power [31:0] $end
$var integer 32 . optimized_power [31:0] $end
$var real 1 / percent_saved $end
$var integer 32 0 saved_power [31:0] $end
$scope module HB $end
$var wire 1 * clk $end
$var wire 1 + reset $end
$var wire 1 , workload_bit $end
$var reg 8 1 hist [7:0] $end
$upscope $end
$scope module MASTER_CORE $end
$var wire 1 ' clk $end
$var reg 8 2 out [7:0] $end
$upscope $end
$scope module MASTER_METER $end
$var wire 1 + reset $end
$var wire 1 3 signal $end
$var wire 1 ' clk $end
$var reg 32 4 count [31:0] $end
$var reg 1 5 prev $end
$upscope $end
$scope module P $end
$var wire 8 6 x [7:0] $end
$var parameter 32 7 BIAS $end
$var parameter 32 8 W0 $end
$var parameter 32 9 W1 $end
$var parameter 32 : W2 $end
$var parameter 32 ; W3 $end
$var parameter 32 < W4 $end
$var parameter 32 = W5 $end
$var parameter 32 > W6 $end
$var parameter 32 ? W7 $end
$var reg 1 $ predict $end
$var integer 32 @ sum [31:0] $end
$upscope $end
$scope module PC $end
$var wire 1 * clk $end
$var wire 1 ' master_clk $end
$var wire 1 $ predict $end
$var wire 1 + reset $end
$var wire 4 A worker_clks [3:0] $end
$var wire 3 B active_count [2:0] $end
$var reg 1 C enable $end
$var reg 1 D latch_en $end
$var reg 6 E warmup [5:0] $end
$upscope $end
$scope module WORKER_CORE $end
$var wire 1 F clk $end
$var reg 8 G out [7:0] $end
$upscope $end
$scope module WORKER_METER $end
$var wire 1 H clk $end
$var wire 1 + reset $end
$var wire 1 I signal $end
$var reg 32 J count [31:0] $end
$var reg 1 K prev $end
$upscope $end
$upscope $end
$enddefinitions $end
$comment Show the parameter values. $end
$dumpall
b1100000 ?
b1010000 >
b1010000 =
b1010000 <
b1110000 ;
b1010000 :
b1100000 9
b1010000 8
b11111111111111111111111011010000 7
$end
#0
$dumpvars
0K
b0 J
0I
0H
b0 G
0F
b0 E
1D
1C
b101 B
b0 A
b11111111111111111111111011010000 @
b0 6
05
b0 4
03
b0 2
b0 1
bx 0
r0 /
bx .
bx -
x,
1+
0*
b101 )
b0 (
0'
b0 &
b0 %
0$
b0 #
b0 "
b0 !
$end
#5000
1I
13
b1 "
b1 G
b1 &
b1 2
1H
1F
b1111 #
b1111 A
1'
1*
#10000
0H
0F
b0 #
b0 A
0'
0*
#15000
0I
03
b10 "
b10 G
b10 &
b10 2
1H
1F
b1111 #
b1111 A
1'
1*
#20000
0H
0F
b0 #
b0 A
0'
0*
1,
0+
#25000
1I
b11111111111111111111111100100000 @
13
b11 "
b11 G
b1 E
b1 (
b1 1
b1 6
b11 &
b11 2
1H
1F
b1111 #
b1111 A
1'
1*
#30000
0H
0F
b0 #
b0 A
0'
0*
#35000
0I
b11111111111111111111111110000000 @
03
1K
b1 !
b1 J
b100 "
b100 G
b11 (
b11 1
b11 6
b10 E
b100 &
b100 2
15
b1 %
b1 4
1H
1F
b1111 #
b1111 A
1'
1*
#40000
0H
0F
b0 #
b0 A
0'
0*
#45000
1I
b11111111111111111111111111010000 @
13
0K
b10 !
b10 J
b101 "
b101 G
b11 E
b111 (
b111 1
b111 6
b101 &
b101 2
05
b10 %
b10 4
1H
1F
b1111 #
b1111 A
1'
1*
#50000
0H
0F
b0 #
b0 A
0'
0*
#55000
0I
1$
b1000000 @
03
1K
b11 !
b11 J
b110 "
b110 G
b1111 (
b1111 1
b1111 6
b100 E
b110 &
b110 2
15
b11 %
b11 4
1H
1F
b1111 #
b1111 A
1'
1*
#60000
0H
0F
b0 #
b0 A
0'
0*
#65000
1I
b10010000 @
13
0K
b100 !
b100 J
b111 "
b111 G
b11111 (
b11111 1
b11111 6
b111 &
b111 2
05
b100 %
b100 4
1H
1F
b1111 #
b1111 A
1'
1*
#70000
0H
0F
b0 #
b0 A
0'
0*
#75000
0I
b11100000 @
03
1K
b101 !
b101 J
b1000 "
b1000 G
b111111 (
b111111 1
b111111 6
b1000 &
b1000 2
15
b101 %
b101 4
1H
1F
b1111 #
b1111 A
1'
1*
#80000
0H
0F
b0 #
b0 A
0'
0*
#85000
1I
b100110000 @
13
0K
b110 !
b110 J
b1001 "
b1001 G
b1111111 (
b1111111 1
b1111111 6
b1001 &
b1001 2
05
b110 %
b110 4
1H
1F
b1111 #
b1111 A
1'
1*
#90000
0H
0F
b0 #
b0 A
0'
0*
#95000
0I
b110010000 @
03
1K
b111 !
b111 J
b1010 "
b1010 G
b11111111 (
b11111111 1
b11111111 6
b1010 &
b1010 2
15
b111 %
b111 4
1H
1F
b1111 #
b1111 A
1'
1*
#100000
0H
0F
b0 #
b0 A
0'
0*
#105000
1I
13
0K
b1000 !
b1000 J
b1011 "
b1011 G
b1011 &
b1011 2
05
b1000 %
b1000 4
1H
1F
b1111 #
b1111 A
1'
1*
#110000
0H
0F
b0 #
b0 A
0'
0*
#115000
0I
03
1K
b1001 !
b1001 J
b1100 "
b1100 G
b1100 &
b1100 2
15
b1001 %
b1001 4
1H
1F
b1111 #
b1111 A
1'
1*
#120000
0H
0F
b0 #
b0 A
0'
0*
#125000
1I
13
0K
b1010 !
b1010 J
b1101 "
b1101 G
b1101 &
b1101 2
05
b1010 %
b1010 4
1H
1F
b1111 #
b1111 A
1'
1*
#130000
0H
0F
b0 #
b0 A
0'
0*
#135000
0I
03
1K
b1011 !
b1011 J
b1110 "
b1110 G
b1110 &
b1110 2
15
b1011 %
b1011 4
1H
1F
b1111 #
b1111 A
1'
1*
#140000
0H
0F
b0 #
b0 A
0'
0*
#145000
1I
13
0K
b1100 !
b1100 J
b1111 "
b1111 G
b1111 &
b1111 2
05
b1100 %
b1100 4
1H
1F
b1111 #
b1111 A
1'
1*
#150000
0H
0F
b0 #
b0 A
0'
0*
#155000
0I
03
1K
b1101 !
b1101 J
b10000 "
b10000 G
b10000 &
b10000 2
15
b1101 %
b1101 4
1H
1F
b1111 #
b1111 A
1'
1*
#160000
0H
0F
b0 #
b0 A
0'
0*
#165000
1I
13
0K
b1110 !
b1110 J
b10001 "
b10001 G
b10001 &
b10001 2
05
b1110 %
b1110 4
1H
1F
b1111 #
b1111 A
1'
1*
#170000
0H
0F
b0 #
b0 A
0'
0*
#175000
0I
03
1K
b1111 !
b1111 J
b10010 "
b10010 G
b10010 &
b10010 2
15
b1111 %
b1111 4
1H
1F
b1111 #
b1111 A
1'
1*
#180000
0H
0F
b0 #
b0 A
0'
0*
#185000
1I
13
0K
b10000 !
b10000 J
b10011 "
b10011 G
b10011 &
b10011 2
05
b10000 %
b10000 4
1H
1F
b1111 #
b1111 A
1'
1*
#190000
0H
0F
b0 #
b0 A
0'
0*
#195000
0I
03
1K
b10001 !
b10001 J
b10100 "
b10100 G
b10100 &
b10100 2
15
b10001 %
b10001 4
1H
1F
b1111 #
b1111 A
1'
1*
#200000
0H
0F
b0 #
b0 A
0'
0*
#205000
1I
13
0K
b10010 !
b10010 J
b10101 "
b10101 G
b10101 &
b10101 2
05
b10010 %
b10010 4
1H
1F
b1111 #
b1111 A
1'
1*
#210000
0H
0F
b0 #
b0 A
0'
0*
#215000
0I
03
1K
b10011 !
b10011 J
b10110 "
b10110 G
b10110 &
b10110 2
15
b10011 %
b10011 4
1H
1F
b1111 #
b1111 A
1'
1*
#220000
0H
0F
b0 #
b0 A
0'
0*
#225000
1I
13
0K
b10100 !
b10100 J
b10111 "
b10111 G
b10111 &
b10111 2
05
b10100 %
b10100 4
1H
1F
b1111 #
b1111 A
1'
1*
#230000
0H
0F
b0 #
b0 A
0'
0*
#235000
0I
03
1K
b10101 !
b10101 J
b11000 "
b11000 G
b11000 &
b11000 2
15
b10101 %
b10101 4
1H
1F
b1111 #
b1111 A
1'
1*
#240000
0H
0F
b0 #
b0 A
0'
0*
#245000
1I
13
0K
b10110 !
b10110 J
b11001 "
b11001 G
b11001 &
b11001 2
05
b10110 %
b10110 4
1H
1F
b1111 #
b1111 A
1'
1*
#250000
0H
0F
b0 #
b0 A
0'
0*
#255000
0I
03
1K
b10111 !
b10111 J
b11010 "
b11010 G
b11010 &
b11010 2
15
b10111 %
b10111 4
1H
1F
b1111 #
b1111 A
1'
1*
#260000
0H
0F
b0 #
b0 A
0'
0*
#265000
1I
13
0K
b11000 !
b11000 J
b11011 "
b11011 G
b11011 &
b11011 2
05
b11000 %
b11000 4
1H
1F
b1111 #
b1111 A
1'
1*
#270000
0H
0F
b0 #
b0 A
0'
0*
#275000
0I
03
1K
b11001 !
b11001 J
b11100 "
b11100 G
b11100 &
b11100 2
15
b11001 %
b11001 4
1H
1F
b1111 #
b1111 A
1'
1*
#280000
0H
0F
b0 #
b0 A
0'
0*
#285000
1I
13
0K
b11010 !
b11010 J
b11101 "
b11101 G
b11101 &
b11101 2
05
b11010 %
b11010 4
1H
1F
b1111 #
b1111 A
1'
1*
#290000
0H
0F
b0 #
b0 A
0'
0*
#295000
0I
03
1K
b11011 !
b11011 J
b11110 "
b11110 G
b11110 &
b11110 2
15
b11011 %
b11011 4
1H
1F
b1111 #
b1111 A
1'
1*
#300000
0H
0F
b0 #
b0 A
0'
0*
#305000
1I
13
0K
b11100 !
b11100 J
b11111 "
b11111 G
b11111 &
b11111 2
05
b11100 %
b11100 4
1H
1F
b1111 #
b1111 A
1'
1*
#310000
0H
0F
b0 #
b0 A
0'
0*
#315000
0I
03
1K
b11101 !
b11101 J
b100000 "
b100000 G
b100000 &
b100000 2
15
b11101 %
b11101 4
1H
1F
b1111 #
b1111 A
1'
1*
#320000
0H
0F
b0 #
b0 A
0'
0*
0,
#325000
1I
b101000000 @
13
0K
b11110 !
b11110 J
b100001 "
b100001 G
b11111110 (
b11111110 1
b11111110 6
b100001 &
b100001 2
05
b11110 %
b11110 4
1H
1F
b1111 #
b1111 A
1'
1*
#330000
0H
0F
b0 #
b0 A
0'
0*
#335000
0I
b11100000 @
03
1K
b11111 !
b11111 J
b100010 "
b100010 G
b11111100 (
b11111100 1
b11111100 6
b100010 &
b100010 2
15
b11111 %
b11111 4
1H
1F
b1111 #
b1111 A
1'
1*
#340000
0H
0F
b0 #
b0 A
0'
0*
#345000
1I
b10010000 @
13
0K
b100000 !
b100000 J
b100011 "
b100011 G
b11111000 (
b11111000 1
b11111000 6
b100011 &
b100011 2
05
b100000 %
b100000 4
1H
1F
b1111 #
b1111 A
1'
1*
#350000
0H
0F
b0 #
b0 A
0'
0*
#355000
0I
b100000 @
03
1K
b100001 !
b100001 J
b100100 "
b100100 G
b11110000 (
b11110000 1
b11110000 6
b100100 &
b100100 2
15
b100001 %
b100001 4
1H
1F
b1111 #
b1111 A
1'
1*
#360000
0H
0F
b0 #
b0 A
0'
0*
#365000
1I
0$
b11111111111111111111111111010000 @
13
0K
b100010 !
b100010 J
b100101 "
b100101 G
b11100000 (
b11100000 1
b11100000 6
b100101 &
b100101 2
05
b100010 %
b100010 4
1H
1F
b1111 #
b1111 A
1'
1*
#370000
0H
0F
b0 #
b0 A
0'
0*
#375000
0I
b11111111111111111111111110000000 @
b1 )
b1 B
03
1K
b100011 !
b100011 J
b100110 "
b100110 G
b11000000 (
b11000000 1
b11000000 6
0C
b100110 &
b100110 2
15
b100011 %
b100011 4
1H
1F
b1111 #
b1111 A
1'
1*
#380000
0D
0H
0F
b0 #
b0 A
0'
0*
#385000
b11111111111111111111111100110000 @
13
b10000000 (
b10000000 1
b10000000 6
b100111 &
b100111 2
05
b100100 %
b100100 4
1'
1*
#390000
0'
0*
#395000
b11111111111111111111111011010000 @
03
b0 (
b0 1
b0 6
b101000 &
b101000 2
15
b100101 %
b100101 4
1'
1*
#400000
0'
0*
#405000
13
b101001 &
b101001 2
05
b100110 %
b100110 4
1'
1*
#410000
0'
0*
#415000
03
b101010 &
b101010 2
15
b100111 %
b100111 4
1'
1*
#420000
0'
0*
#425000
13
b101011 &
b101011 2
05
b101000 %
b101000 4
1'
1*
#430000
0'
0*
#435000
03
b101100 &
b101100 2
15
b101001 %
b101001 4
1'
1*
#440000
0'
0*
#445000
13
b101101 &
b101101 2
05
b101010 %
b101010 4
1'
1*
#450000
0'
0*
#455000
03
b101110 &
b101110 2
15
b101011 %
b101011 4
1'
1*
#460000
0'
0*
#465000
13
b101111 &
b101111 2
05
b101100 %
b101100 4
1'
1*
#470000
0'
0*
#475000
03
b110000 &
b110000 2
15
b101101 %
b101101 4
1'
1*
#480000
0'
0*
#485000
13
b110001 &
b110001 2
05
b101110 %
b101110 4
1'
1*
#490000
0'
0*
#495000
03
b110010 &
b110010 2
15
b101111 %
b101111 4
1'
1*
#500000
0'
0*
#505000
13
b110011 &
b110011 2
05
b110000 %
b110000 4
1'
1*
#510000
0'
0*
#515000
03
b110100 &
b110100 2
15
b110001 %
b110001 4
1'
1*
#520000
0'
0*
#525000
13
b110101 &
b110101 2
05
b110010 %
b110010 4
1'
1*
#530000
0'
0*
#535000
03
b110110 &
b110110 2
15
b110011 %
b110011 4
1'
1*
#540000
0'
0*
#545000
13
b110111 &
b110111 2
05
b110100 %
b110100 4
1'
1*
#550000
0'
0*
#555000
03
b111000 &
b111000 2
15
b110101 %
b110101 4
1'
1*
#560000
0'
0*
#565000
13
b111001 &
b111001 2
05
b110110 %
b110110 4
1'
1*
#570000
0'
0*
#575000
03
b111010 &
b111010 2
15
b110111 %
b110111 4
1'
1*
#580000
0'
0*
#585000
13
b111011 &
b111011 2
05
b111000 %
b111000 4
1'
1*
#590000
0'
0*
#595000
03
b111100 &
b111100 2
15
b111001 %
b111001 4
1'
1*
#600000
0'
0*
#605000
13
b111101 &
b111101 2
05
b111010 %
b111010 4
1'
1*
#610000
0'
0*
#615000
03
b111110 &
b111110 2
15
b111011 %
b111011 4
1'
1*
#620000
0'
0*
#625000
13
b111111 &
b111111 2
05
b111100 %
b111100 4
1'
1*
#630000
0'
0*
#635000
03
b1000000 &
b1000000 2
15
b111101 %
b111101 4
1'
1*
#640000
0'
0*
#645000
13
b1000001 &
b1000001 2
05
b111110 %
b111110 4
1'
1*
#650000
0'
0*
#655000
03
b1000010 &
b1000010 2
15
b111111 %
b111111 4
1'
1*
#660000
0'
0*
#665000
13
b1000011 &
b1000011 2
05
b1000000 %
b1000000 4
1'
1*
#670000
0'
0*
#675000
03
b1000100 &
b1000100 2
15
b1000001 %
b1000001 4
1'
1*
#680000
0'
0*
#685000
13
b1000101 &
b1000101 2
05
b1000010 %
b1000010 4
1'
1*
#690000
0'
0*
#695000
03
b1000110 &
b1000110 2
15
b1000011 %
b1000011 4
1'
1*
#700000
0'
0*
#705000
13
b1000111 &
b1000111 2
05
b1000100 %
b1000100 4
1'
1*
#710000
0'
0*
#715000
03
b1001000 &
b1001000 2
15
b1000101 %
b1000101 4
1'
1*
#720000
0'
0*
#725000
13
b1001001 &
b1001001 2
05
b1000110 %
b1000110 4
1'
1*
#730000
0'
0*
#735000
03
b1001010 &
b1001010 2
15
b1000111 %
b1000111 4
1'
1*
#740000
0'
0*
#745000
13
b1001011 &
b1001011 2
05
b1001000 %
b1001000 4
1'
1*
#750000
0'
0*
#755000
03
b1001100 &
b1001100 2
15
b1001001 %
b1001001 4
1'
1*
#760000
0'
0*
#765000
13
b1001101 &
b1001101 2
05
b1001010 %
b1001010 4
1'
1*
#770000
0'
0*
#775000
03
b1001110 &
b1001110 2
15
b1001011 %
b1001011 4
1'
1*
#780000
0'
0*
#785000
13
b1001111 &
b1001111 2
05
b1001100 %
b1001100 4
1'
1*
#790000
0'
0*
#795000
03
b1010000 &
b1010000 2
15
b1001101 %
b1001101 4
1'
1*
#800000
0'
0*
#805000
13
b1010001 &
b1010001 2
05
b1001110 %
b1001110 4
1'
1*
#810000
0'
0*
#815000
03
b1010010 &
b1010010 2
15
b1001111 %
b1001111 4
1'
1*
#820000
0'
0*
#825000
13
b1010011 &
b1010011 2
05
b1010000 %
b1010000 4
1'
1*
#830000
0'
0*
#835000
03
b1010100 &
b1010100 2
15
b1010001 %
b1010001 4
1'
1*
#840000
0'
0*
#845000
13
b1010101 &
b1010101 2
05
b1010010 %
b1010010 4
1'
1*
#850000
0'
0*
#855000
03
b1010110 &
b1010110 2
15
b1010011 %
b1010011 4
1'
1*
#860000
0'
0*
#865000
13
b1010111 &
b1010111 2
05
b1010100 %
b1010100 4
1'
1*
#870000
0'
0*
#875000
03
b1011000 &
b1011000 2
15
b1010101 %
b1010101 4
1'
1*
#880000
0'
0*
#885000
13
b1011001 &
b1011001 2
05
b1010110 %
b1010110 4
1'
1*
#890000
0'
0*
#895000
03
b1011010 &
b1011010 2
15
b1010111 %
b1010111 4
1'
1*
#900000
0'
0*
#905000
13
b1011011 &
b1011011 2
05
b1011000 %
b1011000 4
1'
1*
#910000
0'
0*
#915000
03
b1011100 &
b1011100 2
15
b1011001 %
b1011001 4
1'
1*
#920000
0'
0*
#925000
13
b1011101 &
b1011101 2
05
b1011010 %
b1011010 4
1'
1*
#930000
0'
0*
#935000
03
b1011110 &
b1011110 2
15
b1011011 %
b1011011 4
1'
1*
#940000
0'
0*
#945000
13
b1011111 &
b1011111 2
05
b1011100 %
b1011100 4
1'
1*
#950000
0'
0*
#955000
03
b1100000 &
b1100000 2
15
b1011101 %
b1011101 4
1'
1*
#960000
0'
0*
#965000
13
b1100001 &
b1100001 2
05
b1011110 %
b1011110 4
1'
1*
#970000
0'
0*
#975000
03
b1100010 &
b1100010 2
15
b1011111 %
b1011111 4
1'
1*
#980000
0'
0*
#985000
13
b1100011 &
b1100011 2
05
b1100000 %
b1100000 4
1'
1*
#990000
0'
0*
#995000
03
b1100100 &
b1100100 2
15
b1100001 %
b1100001 4
1'
1*
#1000000
0'
0*
#1005000
13
b1100101 &
b1100101 2
05
b1100010 %
b1100010 4
1'
1*
#1010000
0'
0*
#1015000
03
b1100110 &
b1100110 2
15
b1100011 %
b1100011 4
1'
1*
#1020000
0'
0*
#1025000
13
b1100111 &
b1100111 2
05
b1100100 %
b1100100 4
1'
1*
#1030000
0'
0*
#1035000
03
b1101000 &
b1101000 2
15
b1100101 %
b1100101 4
1'
1*
#1040000
0'
0*
#1045000
13
b1101001 &
b1101001 2
05
b1100110 %
b1100110 4
1'
1*
#1050000
0'
0*
#1055000
03
b1101010 &
b1101010 2
15
b1100111 %
b1100111 4
1'
1*
#1060000
0'
0*
#1065000
13
b1101011 &
b1101011 2
05
b1101000 %
b1101000 4
1'
1*
#1070000
0'
0*
#1075000
03
b1101100 &
b1101100 2
15
b1101001 %
b1101001 4
1'
1*
#1080000
0'
0*
#1085000
13
b1101101 &
b1101101 2
05
b1101010 %
b1101010 4
1'
1*
#1090000
0'
0*
#1095000
03
b1101110 &
b1101110 2
15
b1101011 %
b1101011 4
1'
1*
#1100000
0'
0*
#1105000
13
b1101111 &
b1101111 2
05
b1101100 %
b1101100 4
1'
1*
#1110000
0'
0*
#1115000
03
b1110000 &
b1110000 2
15
b1101101 %
b1101101 4
1'
1*
#1120000
0'
0*
#1125000
13
b1110001 &
b1110001 2
05
b1101110 %
b1101110 4
1'
1*
#1130000
0'
0*
#1135000
03
b1110010 &
b1110010 2
15
b1101111 %
b1101111 4
1'
1*
#1140000
0'
0*
#1145000
13
b1110011 &
b1110011 2
05
b1110000 %
b1110000 4
1'
1*
#1150000
0'
0*
#1155000
03
b1110100 &
b1110100 2
15
b1110001 %
b1110001 4
1'
1*
#1160000
0'
0*
#1165000
13
b1110101 &
b1110101 2
05
b1110010 %
b1110010 4
1'
1*
#1170000
0'
0*
#1175000
03
b1110110 &
b1110110 2
15
b1110011 %
b1110011 4
1'
1*
#1180000
0'
0*
#1185000
13
b1110111 &
b1110111 2
05
b1110100 %
b1110100 4
1'
1*
#1190000
0'
0*
#1195000
03
b1111000 &
b1111000 2
15
b1110101 %
b1110101 4
1'
1*
#1200000
0'
0*
#1205000
13
b1111001 &
b1111001 2
05
b1110110 %
b1110110 4
1'
1*
#1210000
0'
0*
#1215000
03
b1111010 &
b1111010 2
15
b1110111 %
b1110111 4
1'
1*
#1220000
0'
0*
#1225000
13
b1111011 &
b1111011 2
05
b1111000 %
b1111000 4
1'
1*
#1230000
0'
0*
#1235000
03
b1111100 &
b1111100 2
15
b1111001 %
b1111001 4
1'
1*
#1240000
0'
0*
#1245000
13
b1111101 &
b1111101 2
05
b1111010 %
b1111010 4
1'
1*
#1250000
0'
0*
#1255000
03
b1111110 &
b1111110 2
15
b1111011 %
b1111011 4
1'
1*
#1260000
0'
0*
#1265000
13
b1111111 &
b1111111 2
05
b1111100 %
b1111100 4
1'
1*
#1270000
0'
0*
#1275000
03
b10000000 &
b10000000 2
15
b1111101 %
b1111101 4
1'
1*
#1280000
0'
0*
#1285000
13
b10000001 &
b10000001 2
05
b1111110 %
b1111110 4
1'
1*
#1290000
0'
0*
#1295000
03
b10000010 &
b10000010 2
15
b1111111 %
b1111111 4
1'
1*
#1300000
0'
0*
#1305000
13
b10000011 &
b10000011 2
05
b10000000 %
b10000000 4
1'
1*
#1310000
0'
0*
#1315000
03
b10000100 &
b10000100 2
15
b10000001 %
b10000001 4
1'
1*
#1320000
0'
0*
#1325000
13
b10000101 &
b10000101 2
05
b10000010 %
b10000010 4
1'
1*
#1330000
0'
0*
#1335000
03
b10000110 &
b10000110 2
15
b10000011 %
b10000011 4
1'
1*
#1340000
0'
0*
#1345000
13
b10000111 &
b10000111 2
05
b10000100 %
b10000100 4
1'
1*
#1350000
0'
0*
#1355000
03
b10001000 &
b10001000 2
15
b10000101 %
b10000101 4
1'
1*
#1360000
0'
0*
#1365000
13
b10001001 &
b10001001 2
05
b10000110 %
b10000110 4
1'
1*
#1370000
0'
0*
#1375000
03
b10001010 &
b10001010 2
15
b10000111 %
b10000111 4
1'
1*
#1380000
0'
0*
#1385000
13
b10001011 &
b10001011 2
05
b10001000 %
b10001000 4
1'
1*
#1390000
0'
0*
#1395000
03
b10001100 &
b10001100 2
15
b10001001 %
b10001001 4
1'
1*
#1400000
0'
0*
#1405000
13
b10001101 &
b10001101 2
05
b10001010 %
b10001010 4
1'
1*
#1410000
0'
0*
#1415000
03
b10001110 &
b10001110 2
15
b10001011 %
b10001011 4
1'
1*
#1420000
0'
0*
#1425000
13
b10001111 &
b10001111 2
05
b10001100 %
b10001100 4
1'
1*
#1430000
0'
0*
#1435000
03
b10010000 &
b10010000 2
15
b10001101 %
b10001101 4
1'
1*
#1440000
0'
0*
#1445000
13
b10010001 &
b10010001 2
05
b10001110 %
b10001110 4
1'
1*
#1450000
0'
0*
#1455000
03
b10010010 &
b10010010 2
15
b10001111 %
b10001111 4
1'
1*
#1460000
0'
0*
#1465000
13
b10010011 &
b10010011 2
05
b10010000 %
b10010000 4
1'
1*
#1470000
0'
0*
#1475000
03
b10010100 &
b10010100 2
15
b10010001 %
b10010001 4
1'
1*
#1480000
0'
0*
#1485000
13
b10010101 &
b10010101 2
05
b10010010 %
b10010010 4
1'
1*
#1490000
0'
0*
#1495000
03
b10010110 &
b10010110 2
15
b10010011 %
b10010011 4
1'
1*
#1500000
0'
0*
#1505000
13
b10010111 &
b10010111 2
05
b10010100 %
b10010100 4
1'
1*
#1510000
0'
0*
#1515000
03
b10011000 &
b10011000 2
15
b10010101 %
b10010101 4
1'
1*
#1520000
0'
0*
#1525000
13
b10011001 &
b10011001 2
05
b10010110 %
b10010110 4
1'
1*
#1530000
0'
0*
#1535000
03
b10011010 &
b10011010 2
15
b10010111 %
b10010111 4
1'
1*
#1540000
0'
0*
#1545000
13
b10011011 &
b10011011 2
05
b10011000 %
b10011000 4
1'
1*
#1550000
0'
0*
#1555000
03
b10011100 &
b10011100 2
15
b10011001 %
b10011001 4
1'
1*
#1560000
0'
0*
#1565000
13
b10011101 &
b10011101 2
05
b10011010 %
b10011010 4
1'
1*
#1570000
0'
0*
#1575000
03
b10011110 &
b10011110 2
15
b10011011 %
b10011011 4
1'
1*
#1580000
0'
0*
#1585000
13
b10011111 &
b10011111 2
05
b10011100 %
b10011100 4
1'
1*
#1590000
0'
0*
#1595000
03
b10100000 &
b10100000 2
15
b10011101 %
b10011101 4
1'
1*
#1600000
0'
0*
#1605000
13
b10100001 &
b10100001 2
05
b10011110 %
b10011110 4
1'
1*
#1610000
0'
0*
#1615000
03
b10100010 &
b10100010 2
15
b10011111 %
b10011111 4
1'
1*
#1620000
0'
0*
#1625000
13
b10100011 &
b10100011 2
05
b10100000 %
b10100000 4
1'
1*
#1630000
0'
0*
#1635000
03
b10100100 &
b10100100 2
15
b10100001 %
b10100001 4
1'
1*
#1640000
0'
0*
