switch_counter.v
module switch_counter(
    input clk,
    input reset,
    input signal,
    output reg [31:0] count
);

reg prev;

always @(posedge clk or posedge reset) begin
    if(reset) begin
        count <= 0;
        prev <= 0;
    end
    else begin
        if(signal != prev)
            count <= count + 1;
        prev <= signal;
    end
end

endmodule

power_controller.v
module power_controller(
    input clk,
    input reset,
    input predict,
    output gated_clk
);

reg enable;
reg [5:0] warmup = 0;

always @(posedge clk or posedge reset) begin
    if(reset) begin
        warmup <= 0;
        enable <= 1;
    end
    else begin
        if(warmup < 4) begin
            warmup <= warmup + 1;
            enable <= 1;          // force ON during warmup
        end
        else begin
            enable <= predict;    // ML controls after warmup
        end
    end
end

assign gated_clk = enable ? clk : 1'b0;

endmodule

dummy_alu.v
module dummy_alu(
    input clk,
    output reg [7:0] out
);

initial out = 0;

always @(posedge clk)
    out <= out + 1;

endmodule

perceptron.v
module perceptron(
    input [7:0] x,
    output reg predict
);

// ----- PASTE YOUR VALUES -----
parameter signed W0 = 80;
parameter signed W1 = 80;
parameter signed W2 = 64;
parameter signed W3 = 64;
parameter signed W4 = 64;
parameter signed W5 = 112;
parameter signed W6 = 80;
parameter signed W7 = 96;
parameter signed BIAS = -240;
// -----------------------------

integer sum;

always @(*) begin
    sum = BIAS;
    if(x[0]) sum = sum + W0;
    if(x[1]) sum = sum + W1;
    if(x[2]) sum = sum + W2;
    if(x[3]) sum = sum + W3;
    if(x[4]) sum = sum + W4;
    if(x[5]) sum = sum + W5;
    if(x[6]) sum = sum + W6;
    if(x[7]) sum = sum + W7;

    if(sum >= 0)
        predict = 1;
    else
        predict = 0;
end
endmodule

history_buffer.v
module history_buffer(
    input clk,
    input reset,
    input workload_bit,
    output reg [7:0] hist
);
always @(posedge clk or posedge reset) begin
    if(reset)
        hist <= 8'b0;
    else
        hist <= {hist[6:0], workload_bit};
end
endmodule

tb.v
module tb;

reg clk = 0;
reg reset = 1;
reg workload;

wire [7:0] hist;
wire predict;
wire [7:0] alu_out;

wire [31:0] toggle_count;

always #5 clk = ~clk;   // 100MHz
// wire gated_clk = clk;   // force always ON

// Instantiate modules
history_buffer HB(clk, reset, workload, hist);
perceptron P(hist, predict);
dummy_alu ALU(gated_clk, alu_out);
power_controller PC(clk, reset, predict, gated_clk);
switch_counter SW(gated_clk, reset, alu_out[0], toggle_count);




initial begin
    $dumpfile("wave.vcd");
    $dumpvars(0,tb);

    reset = 1;
    #20 reset = 0;

    // -------- WORKLOAD PATTERN --------
    // Burst phase
// Long ACTIVE phase
// Active
repeat(40) begin workload = 1; #10; end

// Huge idle, ML should dominate
repeat(200) begin workload = 0; #10; end

// Mixed
repeat(60) begin workload = ( ($time/10) % 5 != 0 ); #10; end

    
    #2000;
    $display("FINAL SWITCHING COUNT = %d", toggle_count);
    $finish;
end
endmodule

wave.vcd
$date
	Fri Jan 02 10:39:04 2026
$end
$version
	Icarus Verilog
$end
$timescale
	1s
$end
$scope module tb $end
$var wire 32 ! toggle_count [31:0] $end
$var wire 1 " predict $end
$var wire 8 # hist [7:0] $end
$var wire 1 $ gated_clk $end
$var wire 8 % alu_out [7:0] $end
$var reg 1 & clk $end
$var reg 1 ' reset $end
$var reg 1 ( workload $end
$scope module ALU $end
$var wire 1 $ clk $end
$var reg 8 ) out [7:0] $end
$upscope $end
$scope module HB $end
$var wire 1 & clk $end
$var wire 1 ' reset $end
$var wire 1 ( workload_bit $end
$var reg 8 * hist [7:0] $end
$upscope $end
$scope module P $end
$var wire 8 + x [7:0] $end
$var parameter 32 , BIAS $end
$var parameter 32 - W0 $end
$var parameter 32 . W1 $end
$var parameter 32 / W2 $end
$var parameter 32 0 W3 $end
$var parameter 32 1 W4 $end
$var parameter 32 2 W5 $end
$var parameter 32 3 W6 $end
$var parameter 32 4 W7 $end
$var reg 1 " predict $end
$var integer 32 5 sum [31:0] $end
$upscope $end
$scope module PC $end
$var wire 1 & clk $end
$var wire 1 " predict $end
$var wire 1 ' reset $end
$var wire 1 $ gated_clk $end
$var reg 1 6 enable $end
$var reg 6 7 warmup [5:0] $end
$upscope $end
$scope module SW $end
$var wire 1 $ clk $end
$var wire 1 ' reset $end
$var wire 1 8 signal $end
$var reg 32 9 count [31:0] $end
$var reg 1 : prev $end
$upscope $end
$upscope $end
$enddefinitions $end
$comment Show the parameter values. $end
$dumpall
b1100000 4
b1010000 3
b1110000 2
b1000000 1
b1000000 0
b1000000 /
b1010000 .
b1010000 -
b11111111111111111111111100010000 ,
$end
#0
$dumpvars
0:
b0 9
08
b0 7
16
b11111111111111111111111100010000 5
b0 +
b0 *
b0 )
x(
1'
0&
b0 %
0$
b0 #
0"
b0 !
$end
#5
18
b1 %
b1 )
1$
1&
#10
0$
0&
#15
08
b10 %
b10 )
1$
1&
#20
0$
0&
1(
0'
#25
18
b11111111111111111111111101100000 5
b11 %
b11 )
b1 7
b1 #
b1 *
b1 +
1$
1&
#30
0$
0&
#35
08
b11111111111111111111111110110000 5
b100 %
b100 )
1:
b1 !
b1 9
b11 #
b11 *
b11 +
b10 7
1$
1&
#40
0$
0&
#45
18
b11111111111111111111111111110000 5
b101 %
b101 )
0:
b10 !
b10 9
b11 7
b111 #
b111 *
b111 +
1$
1&
#50
0$
0&
#55
08
1"
b110000 5
b110 %
b110 )
1:
b11 !
b11 9
b1111 #
b1111 *
b1111 +
b100 7
1$
1&
#60
0$
0&
#65
18
b1110000 5
b111 %
b111 )
0:
b100 !
b100 9
b11111 #
b11111 *
b11111 +
1$
1&
#70
0$
0&
#75
08
b11100000 5
b1000 %
b1000 )
1:
b101 !
b101 9
b111111 #
b111111 *
b111111 +
1$
1&
#80
0$
0&
#85
18
b100110000 5
b1001 %
b1001 )
0:
b110 !
b110 9
b1111111 #
b1111111 *
b1111111 +
1$
1&
#90
0$
0&
#95
08
b110010000 5
b1010 %
b1010 )
1:
b111 !
b111 9
b11111111 #
b11111111 *
b11111111 +
1$
1&
#100
0$
0&
#105
18
b1011 %
b1011 )
0:
b1000 !
b1000 9
1$
1&
#110
0$
0&
#115
08
b1100 %
b1100 )
1:
b1001 !
b1001 9
1$
1&
#120
0$
0&
#125
18
b1101 %
b1101 )
0:
b1010 !
b1010 9
1$
1&
#130
0$
0&
#135
08
b1110 %
b1110 )
1:
b1011 !
b1011 9
1$
1&
#140
0$
0&
#145
18
b1111 %
b1111 )
0:
b1100 !
b1100 9
1$
1&
#150
0$
0&
#155
08
b10000 %
b10000 )
1:
b1101 !
b1101 9
1$
1&
#160
0$
0&
#165
18
b10001 %
b10001 )
0:
b1110 !
b1110 9
1$
1&
#170
0$
0&
#175
08
b10010 %
b10010 )
1:
b1111 !
b1111 9
1$
1&
#180
0$
0&
#185
18
b10011 %
b10011 )
0:
b10000 !
b10000 9
1$
1&
#190
0$
0&
#195
08
b10100 %
b10100 )
1:
b10001 !
b10001 9
1$
1&
#200
0$
0&
#205
18
b10101 %
b10101 )
0:
b10010 !
b10010 9
1$
1&
#210
0$
0&
#215
08
b10110 %
b10110 )
1:
b10011 !
b10011 9
1$
1&
#220
0$
0&
#225
18
b10111 %
b10111 )
0:
b10100 !
b10100 9
1$
1&
#230
0$
0&
#235
08
b11000 %
b11000 )
1:
b10101 !
b10101 9
1$
1&
#240
0$
0&
#245
18
b11001 %
b11001 )
0:
b10110 !
b10110 9
1$
1&
#250
0$
0&
#255
08
b11010 %
b11010 )
1:
b10111 !
b10111 9
1$
1&
#260
0$
0&
#265
18
b11011 %
b11011 )
0:
b11000 !
b11000 9
1$
1&
#270
0$
0&
#275
08
b11100 %
b11100 )
1:
b11001 !
b11001 9
1$
1&
#280
0$
0&
#285
18
b11101 %
b11101 )
0:
b11010 !
b11010 9
1$
1&
#290
0$
0&
#295
08
b11110 %
b11110 )
1:
b11011 !
b11011 9
1$
1&
#300
0$
0&
#305
18
b11111 %
b11111 )
0:
b11100 !
b11100 9
1$
1&
#310
0$
0&
#315
08
b100000 %
b100000 )
1:
b11101 !
b11101 9
1$
1&
#320
0$
0&
#325
18
b100001 %
b100001 )
0:
b11110 !
b11110 9
1$
1&
#330
0$
0&
#335
08
b100010 %
b100010 )
1:
b11111 !
b11111 9
1$
1&
#340
0$
0&
#345
18
b100011 %
b100011 )
0:
b100000 !
b100000 9
1$
1&
#350
0$
0&
#355
08
b100100 %
b100100 )
1:
b100001 !
b100001 9
1$
1&
#360
0$
0&
#365
18
b100101 %
b100101 )
0:
b100010 !
b100010 9
1$
1&
#370
0$
0&
#375
08
b100110 %
b100110 )
1:
b100011 !
b100011 9
1$
1&
#380
0$
0&
#385
18
b100111 %
b100111 )
0:
b100100 !
b100100 9
1$
1&
#390
0$
0&
#395
08
b101000 %
b101000 )
1:
b100101 !
b100101 9
1$
1&
#400
0$
0&
#405
18
b101001 %
b101001 )
0:
b100110 !
b100110 9
1$
1&
#410
0$
0&
#415
08
b101010 %
b101010 )
1:
b100111 !
b100111 9
1$
1&
#420
0$
0&
0(
#425
18
b101000000 5
b101011 %
b101011 )
0:
b101000 !
b101000 9
b11111110 #
b11111110 *
b11111110 +
1$
1&
#430
0$
0&
#435
08
b11110000 5
b101100 %
b101100 )
1:
b101001 !
b101001 9
b11111100 #
b11111100 *
b11111100 +
1$
1&
#440
0$
0&
#445
18
b10110000 5
b101101 %
b101101 )
0:
b101010 !
b101010 9
b11111000 #
b11111000 *
b11111000 +
1$
1&
#450
0$
0&
#455
08
b1110000 5
b101110 %
b101110 )
1:
b101011 !
b101011 9
b11110000 #
b11110000 *
b11110000 +
1$
1&
#460
0$
0&
#465
18
b110000 5
b101111 %
b101111 )
0:
b101100 !
b101100 9
b11100000 #
b11100000 *
b11100000 +
1$
1&
#470
0$
0&
#475
08
0"
b11111111111111111111111111000000 5
b110000 %
b110000 )
1:
b101101 !
b101101 9
b11000000 #
b11000000 *
b11000000 +
1$
1&
#480
0$
0&
#485
18
b11111111111111111111111101110000 5
b110001 %
b110001 )
0:
b101110 !
b101110 9
06
b10000000 #
b10000000 *
b10000000 +
0$
1&
#490
0&
#495
b11111111111111111111111100010000 5
b0 #
b0 *
b0 +
1&
